<annotation>
	<folder>DeepPiCar</folder>
	<filename>2020-05-16-190509.jpg</filename>
	<path>D:\Users\kpchi\Documents\CS docs and notes\Kal Academy AI Bootcamp\DeepPiCar\2020-05-16-190509.jpg</path>
	<source>
		<database>Unknown</database>
	</source>
	<size>
		<width>640</width>
		<height>480</height>
		<depth>3</depth>
	</size>
	<segmented>0</segmented>
	<object>
		<name>StopSign</name>
		<pose>Unspecified</pose>
		<truncated>0</truncated>
		<difficult>0</difficult>
		<bndbox>
			<xmin>353</xmin>
			<ymin>204</ymin>
			<xmax>389</xmax>
			<ymax>237</ymax>
		</bndbox>
	</object>
	<object>
		<name>TrafficLight</name>
		<pose>Unspecified</pose>
		<truncated>0</truncated>
		<difficult>0</difficult>
		<bndbox>
			<xmin>497</xmin>
			<ymin>193</ymin>
			<xmax>537</xmax>
			<ymax>300</ymax>
		</bndbox>
	</object>
	<object>
		<name>TrafficLight</name>
		<pose>Unspecified</pose>
		<truncated>0</truncated>
		<difficult>0</difficult>
		<bndbox>
			<xmin>189</xmin>
			<ymin>196</ymin>
			<xmax>222</xmax>
			<ymax>268</ymax>
		</bndbox>
	</object>
	<object>
		<name>SpeedLimit55</name>
		<pose>Unspecified</pose>
		<truncated>0</truncated>
		<difficult>0</difficult>
		<bndbox>
			<xmin>59</xmin>
			<ymin>175</ymin>
			<xmax>136</xmax>
			<ymax>292</ymax>
		</bndbox>
	</object>
	<object>
		<name>SpeedLimit35</name>
		<pose>Unspecified</pose>
		<truncated>0</truncated>
		<difficult>0</difficult>
		<bndbox>
			<xmin>411</xmin>
			<ymin>190</ymin>
			<xmax>458</xmax>
			<ymax>261</ymax>
		</bndbox>
	</object>
	<object>
		<name>SpeedLimit25</name>
		<pose>Unspecified</pose>
		<truncated>0</truncated>
		<difficult>0</difficult>
		<bndbox>
			<xmin>276</xmin>
			<ymin>191</ymin>
			<xmax>319</xmax>
			<ymax>252</ymax>
		</bndbox>
	</object>
	<object>
		<name>person</name>
		<pose>Unspecified</pose>
		<truncated>0</truncated>
		<difficult>0</difficult>
		<bndbox>
			<xmin>25</xmin>
			<ymin>272</ymin>
			<xmax>67</xmax>
			<ymax>357</ymax>
		</bndbox>
	</object>
	<object>
		<name>person</name>
		<pose>Unspecified</pose>
		<truncated>0</truncated>
		<difficult>0</difficult>
		<bndbox>
			<xmin>251</xmin>
			<ymin>321</ymin>
			<xmax>322</xmax>
			<ymax>455</ymax>
		</bndbox>
	</object>
	<object>
		<name>person</name>
		<pose>Unspecified</pose>
		<truncated>0</truncated>
		<difficult>0</difficult>
		<bndbox>
			<xmin>323</xmin>
			<ymin>254</ymin>
			<xmax>355</xmax>
			<ymax>312</ymax>
		</bndbox>
	</object>
	<object>
		<name>person</name>
		<pose>Unspecified</pose>
		<truncated>0</truncated>
		<difficult>0</difficult>
		<bndbox>
			<xmin>399</xmin>
			<ymin>245</ymin>
			<xmax>414</xmax>
			<ymax>293</ymax>
		</bndbox>
	</object>
</annotation>
